pythonit_toolkit/__init__.py
pythonit_toolkit/api/__init__.py
pythonit_toolkit/api/builder.py
pythonit_toolkit/api/extensions.py
pythonit_toolkit/api/graphql_test_client.py
pythonit_toolkit/api/permissions.py
pythonit_toolkit/api/types.py
pythonit_toolkit/emails/__init__.py
pythonit_toolkit/emails/backends/__init__.py
pythonit_toolkit/emails/backends/base.py
pythonit_toolkit/emails/backends/local.py
pythonit_toolkit/emails/backends/ses.py
pythonit_toolkit/emails/templates.py
pythonit_toolkit/emails/utils.py
pythonit_toolkit/headers/__init__.py
pythonit_toolkit/pastaporto/__init__.py
pythonit_toolkit/pastaporto/actions.py
pythonit_toolkit/pastaporto/entities.py
pythonit_toolkit/pastaporto/exceptions.py
pythonit_toolkit/pastaporto/test.py
pythonit_toolkit/pastaporto/tokens.py
pythonit_toolkit/sentry/__init__.py
pythonit_toolkit/sentry/sentry.py
pythonit_toolkit/service_client/__init__.py
pythonit_toolkit/service_client/client.py
pythonit_toolkit/starlette_backend/__init__.py
pythonit_toolkit/starlette_backend/middleware.py
pythonit_toolkit/starlette_backend/pastaporto_backend.py
pythonit_toolkit-0.1.94.dist-info/LICENSE
pythonit_toolkit-0.1.94.dist-info/METADATA
pythonit_toolkit-0.1.94.dist-info/WHEEL
pythonit_toolkit-0.1.94.dist-info/RECORD
