Metadata-Version: 2.1
Name: pythonit-toolkit
Version: 0.1.94
Summary: 
Author: Python Italia
Requires-Python: >=3.8,<4.0.0
Classifier: Programming Language :: Python :: 3
Classifier: Programming Language :: Python :: 3.8
Classifier: Programming Language :: Python :: 3.9
Classifier: Programming Language :: Python :: 3.10
Classifier: Programming Language :: Python :: 3.11
Classifier: Programming Language :: Python :: 3.12
Requires-Dist: PyJWT (>=2.8.0,<3.0.0)
Requires-Dist: boto3 (>=1.28.9,<2.0.0)
Requires-Dist: httpx (>=0.25.1,<0.26.0)
Requires-Dist: pydantic
Requires-Dist: sentry-sdk (>=1.28.1,<2.0.0)
Requires-Dist: starlette (>=0.30.0,<0.31.0)
Requires-Dist: strawberry-graphql
